odoo8_addon_partner_relations-8.0.1.1.2-py2.7-nspkg.pth
odoo8_addon_partner_relations-8.0.1.1.2.dist-info/DESCRIPTION.rst
odoo8_addon_partner_relations-8.0.1.1.2.dist-info/METADATA
odoo8_addon_partner_relations-8.0.1.1.2.dist-info/RECORD
odoo8_addon_partner_relations-8.0.1.1.2.dist-info/WHEEL
odoo8_addon_partner_relations-8.0.1.1.2.dist-info/metadata.json
odoo8_addon_partner_relations-8.0.1.1.2.dist-info/namespace_packages.txt
odoo8_addon_partner_relations-8.0.1.1.2.dist-info/top_level.txt
odoo_addons/partner_relations/README.rst
odoo_addons/partner_relations/__init__.py
odoo_addons/partner_relations/__openerp__.py
odoo_addons/partner_relations/data/demo.xml
odoo_addons/partner_relations/i18n/da.po
odoo_addons/partner_relations/i18n/de.po
odoo_addons/partner_relations/i18n/es.po
odoo_addons/partner_relations/i18n/eu.po
odoo_addons/partner_relations/i18n/fi.po
odoo_addons/partner_relations/i18n/fr.po
odoo_addons/partner_relations/i18n/it.po
odoo_addons/partner_relations/i18n/nl.po
odoo_addons/partner_relations/i18n/partner_relations.pot
odoo_addons/partner_relations/i18n/pt_BR.po
odoo_addons/partner_relations/i18n/sl.po
odoo_addons/partner_relations/models/__init__.py
odoo_addons/partner_relations/models/res_partner.py
odoo_addons/partner_relations/models/res_partner_relation.py
odoo_addons/partner_relations/models/res_partner_relation_all.py
odoo_addons/partner_relations/models/res_partner_relation_type.py
odoo_addons/partner_relations/models/res_partner_relation_type_selection.py
odoo_addons/partner_relations/security/ir.model.access.csv
odoo_addons/partner_relations/static/description/icon.png
odoo_addons/partner_relations/tests/__init__.py
odoo_addons/partner_relations/tests/test_partner_relation.py
odoo_addons/partner_relations/tests/test_partner_relation_all.py
odoo_addons/partner_relations/tests/test_partner_relation_common.py
odoo_addons/partner_relations/tests/test_partner_search.py
odoo_addons/partner_relations/views/menu.xml
odoo_addons/partner_relations/views/res_partner.xml
odoo_addons/partner_relations/views/res_partner_relation_all.xml
odoo_addons/partner_relations/views/res_partner_relation_type.xml
